{
  "slug": "ciencias-politicas",
  "nombre": "Ciencias Políticas",
  "ofertas": [
    {
      "codigo_unico_carrera": "I2S1C658J1V1",
      "institucion": {
        "codigo": 2,
        "nombre": "Universidad Finis Terrae",
        "tipo": "Universidades",
        "acreditacion": "Acreditada",
        "tiene_ficha": true
      },
      "nombre_carrera_programa": "CIENCIA POLITICA",
      "nivel_carrera": "Profesional",
      "region": "Metropolitana",
      "jornada": "Diurna",
      "sede": "CASA CENTRAL (SANTIAGO)",
      "arancel_anual_2026": "$ 6.000.000",
      "vacantes_1er_semestre": 20.0,
      "tiene_ponderacion_paes": true,
      "ponderacion_nem": 10.0,
      "ponderacion_ranking": 35.0,
      "ponderacion_lenguaje": 20.0,
      "ponderacion_matematicas": 20.0,
      "ponderacion_matematicas_2": 0.0,
      "ponderacion_historia": 15.0,
      "ponderacion_ciencias": 15.0,
      "ponderacion_otros": 0.0
    },
    {
      "codigo_unico_carrera": "I3S1C44J1V1",
      "institucion": {
        "codigo": 3,
        "nombre": "Universidad Diego Portales",
        "tipo": "Universidades",
        "acreditacion": "Acreditada",
        "tiene_ficha": true
      },
      "nombre_carrera_programa": "CIENCIA POLITICA",
      "nivel_carrera": "Profesional",
      "region": "Metropolitana",
      "jornada": "Diurna",
      "sede": "CASA CENTRAL (SANTIAGO)",
      "arancel_anual_2026": "$ 6.993.000",
      "vacantes_1er_semestre": 90.0,
      "tiene_ponderacion_paes": true,
      "ponderacion_nem": 10.0,
      "ponderacion_ranking": 30.0,
      "ponderacion_lenguaje": 25.0,
      "ponderacion_matematicas": 20.0,
      "ponderacion_matematicas_2": 0.0,
      "ponderacion_historia": 15.0,
      "ponderacion_ciencias": 15.0,
      "ponderacion_otros": 0.0
    },
    {
      "codigo_unico_carrera": "I4S1C37J1V2",
      "institucion": {
        "codigo": 4,
        "nombre": "Universidad Central de Chile",
        "tipo": "Universidades",
        "acreditacion": "Acreditada",
        "tiene_ficha": true
      },
      "nombre_carrera_programa": "CIENCIA POLITICA",
      "nivel_carrera": "Profesional",
      "region": "Metropolitana",
      "jornada": "Diurna",
      "sede": "SANTIAGO",
      "arancel_anual_2026": "$ 4.840.000",
      "vacantes_1er_semestre": 40.0,
      "tiene_ponderacion_paes": true,
      "ponderacion_nem": 10.0,
      "ponderacion_ranking": 40.0,
      "ponderacion_lenguaje": 25.0,
      "ponderacion_matematicas": 10.0,
      "ponderacion_matematicas_2": 0.0,
      "ponderacion_historia": 15.0,
      "ponderacion_ciencias": 15.0,
      "ponderacion_otros": 0.0
    },
    {
      "codigo_unico_carrera": "I11S2C34J1V1",
      "institucion": {
        "codigo": 11,
        "nombre": "Universidad Academia de Humanismo Cristiano",
        "tipo": "Universidades",
        "acreditacion": "Acreditada",
        "tiene_ficha": true
      },
      "nombre_carrera_programa": "CIENCIA POLITICA Y RELACIONES INTERNACIONALES",
      "nivel_carrera": "Profesional",
      "region": "Metropolitana",
      "jornada": "Diurna",
      "sede": "CAMPUS REPUBLICA",
      "arancel_anual_2026": "$ 4.245.000",
      "vacantes_1er_semestre": 15.0,
      "tiene_ponderacion_paes": true,
      "ponderacion_nem": 10.0,
      "ponderacion_ranking": 30.0,
      "ponderacion_lenguaje": 30.0,
      "ponderacion_matematicas": 10.0,
      "ponderacion_matematicas_2": 0.0,
      "ponderacion_historia": 20.0,
      "ponderacion_ciencias": 20.0,
      "ponderacion_otros": 0.0
    },
    {
      "codigo_unico_carrera": "I45S4C30J1V1",
      "institucion": {
        "codigo": 45,
        "nombre": "Universidad del Desarrollo",
        "tipo": "Universidades",
        "acreditacion": "Acreditada",
        "tiene_ficha": true
      },
      "nombre_carrera_programa": "CIENCIA POLITICA Y POLITICAS PUBLICAS",
      "nivel_carrera": "Profesional",
      "region": "Metropolitana",
      "jornada": "Diurna",
      "sede": "SEDE SANTIAGO (S.C. APOQUINDO)",
      "arancel_anual_2026": "UF 232",
      "vacantes_1er_semestre": 70.0,
      "tiene_ponderacion_paes": true,
      "ponderacion_nem": 10.0,
      "ponderacion_ranking": 30.0,
      "ponderacion_lenguaje": 25.0,
      "ponderacion_matematicas": 20.0,
      "ponderacion_matematicas_2": 0.0,
      "ponderacion_historia": 15.0,
      "ponderacion_ciencias": 15.0,
      "ponderacion_otros": 0.0
    },
    {
      "codigo_unico_carrera": "I68S1C40J1V1",
      "institucion": {
        "codigo": 68,
        "nombre": "Universidad Miguel de Cervantes",
        "tipo": "Universidades",
        "acreditacion": "Acreditada",
        "tiene_ficha": true
      },
      "nombre_carrera_programa": "CIENCIA POLITICA Y ADMINISTRACION PUBLICA",
      "nivel_carrera": "Profesional",
      "region": "Metropolitana",
      "jornada": "Diurna",
      "sede": "CASA CENTRAL (SANTIAGO)",
      "arancel_anual_2026": "$ 2.100.000",
      "vacantes_1er_semestre": 25.0,
      "tiene_ponderacion_paes": false,
      "ponderacion_nem": 0.0,
      "ponderacion_ranking": 0.0,
      "ponderacion_lenguaje": 0.0,
      "ponderacion_matematicas": 0.0,
      "ponderacion_matematicas_2": 0.0,
      "ponderacion_historia": 0.0,
      "ponderacion_ciencias": 0.0,
      "ponderacion_otros": 0.0
    },
    {
      "codigo_unico_carrera": "I68S1C40J2V1",
      "institucion": {
        "codigo": 68,
        "nombre": "Universidad Miguel de Cervantes",
        "tipo": "Universidades",
        "acreditacion": "Acreditada",
        "tiene_ficha": true
      },
      "nombre_carrera_programa": "CIENCIA POLITICA Y ADMINISTRACION PUBLICA",
      "nivel_carrera": "Profesional",
      "region": "Metropolitana",
      "jornada": "Vespertina",
      "sede": "CASA CENTRAL (SANTIAGO)",
      "arancel_anual_2026": "$ 2.100.000",
      "vacantes_1er_semestre": 20.0,
      "tiene_ponderacion_paes": false,
      "ponderacion_nem": 0.0,
      "ponderacion_ranking": 0.0,
      "ponderacion_lenguaje": 0.0,
      "ponderacion_matematicas": 0.0,
      "ponderacion_matematicas_2": 0.0,
      "ponderacion_historia": 0.0,
      "ponderacion_ciencias": 0.0,
      "ponderacion_otros": 0.0
    },
    {
      "codigo_unico_carrera": "I68S1C40J4V1",
      "institucion": {
        "codigo": 68,
        "nombre": "Universidad Miguel de Cervantes",
        "tipo": "Universidades",
        "acreditacion": "Acreditada",
        "tiene_ficha": true
      },
      "nombre_carrera_programa": "CIENCIA POLITICA Y ADMINISTRACION PUBLICA",
      "nivel_carrera": "Profesional",
      "region": "Metropolitana",
      "jornada": "A Distancia",
      "sede": "CASA CENTRAL (SANTIAGO)",
      "arancel_anual_2026": "$ 2.100.000",
      "vacantes_1er_semestre": 25.0,
      "tiene_ponderacion_paes": false,
      "ponderacion_nem": 0.0,
      "ponderacion_ranking": 0.0,
      "ponderacion_lenguaje": 0.0,
      "ponderacion_matematicas": 0.0,
      "ponderacion_matematicas_2": 0.0,
      "ponderacion_historia": 0.0,
      "ponderacion_ciencias": 0.0,
      "ponderacion_otros": 0.0
    },
    {
      "codigo_unico_carrera": "I69S1C80J1V1",
      "institucion": {
        "codigo": 69,
        "nombre": "Universidad Alberto Hurtado",
        "tipo": "Universidades",
        "acreditacion": "Acreditada",
        "tiene_ficha": true
      },
      "nombre_carrera_programa": "CIENCIA POLITICA Y RELACIONES INTERNACIONALES",
      "nivel_carrera": "Profesional",
      "region": "Metropolitana",
      "jornada": "Diurna",
      "sede": "CASA CENTRAL (SANTIAGO)",
      "arancel_anual_2026": "$ 5.960.441",
      "vacantes_1er_semestre": 100.0,
      "tiene_ponderacion_paes": true,
      "ponderacion_nem": 10.0,
      "ponderacion_ranking": 40.0,
      "ponderacion_lenguaje": 20.0,
      "ponderacion_matematicas": 20.0,
      "ponderacion_matematicas_2": 0.0,
      "ponderacion_historia": 10.0,
      "ponderacion_ciencias": 0.0,
      "ponderacion_otros": 0.0
    },
    {
      "codigo_unico_carrera": "I70S1C911J1V1",
      "institucion": {
        "codigo": 70,
        "nombre": "Universidad de Chile",
        "tipo": "Universidades",
        "acreditacion": "Acreditada",
        "tiene_ficha": true
      },
      "nombre_carrera_programa": "CIENCIA POLITICA",
      "nivel_carrera": "Profesional",
      "region": "Metropolitana",
      "jornada": "Diurna",
      "sede": "SANTIAGO",
      "arancel_anual_2026": "$ 5.715.200",
      "vacantes_1er_semestre": 65.0,
      "tiene_ponderacion_paes": true,
      "ponderacion_nem": 10.0,
      "ponderacion_ranking": 30.0,
      "ponderacion_lenguaje": 20.0,
      "ponderacion_matematicas": 20.0,
      "ponderacion_matematicas_2": 0.0,
      "ponderacion_historia": 20.0,
      "ponderacion_ciencias": 0.0,
      "ponderacion_otros": 0.0
    },
    {
      "codigo_unico_carrera": "I86S5C64J1V1",
      "institucion": {
        "codigo": 86,
        "nombre": "Pontificia Universidad Católica de Chile",
        "tipo": "Universidades",
        "acreditacion": "Acreditada",
        "tiene_ficha": true
      },
      "nombre_carrera_programa": "CIENCIA POLITICA",
      "nivel_carrera": "Profesional",
      "region": "Metropolitana",
      "jornada": "Diurna",
      "sede": "CAMPUS SAN JOAQUIN",
      "arancel_anual_2026": "$ 7.200.000",
      "vacantes_1er_semestre": 35.0,
      "tiene_ponderacion_paes": true,
      "ponderacion_nem": 20.0,
      "ponderacion_ranking": 25.0,
      "ponderacion_lenguaje": 20.0,
      "ponderacion_matematicas": 20.0,
      "ponderacion_matematicas_2": 0.0,
      "ponderacion_historia": 15.0,
      "ponderacion_ciencias": 0.0,
      "ponderacion_otros": 0.0
    },
    {
      "codigo_unico_carrera": "I94S1C56J1V1",
      "institucion": {
        "codigo": 94,
        "nombre": "Universidad Católica de Temuco",
        "tipo": "Universidades",
        "acreditacion": "Acreditada",
        "tiene_ficha": true
      },
      "nombre_carrera_programa": "CIENCIA POLITICA",
      "nivel_carrera": "Profesional",
      "region": "La Araucanía",
      "jornada": "Diurna",
      "sede": "CASA CENTRAL (TEMUCO)",
      "arancel_anual_2026": "$ 4.638.000",
      "vacantes_1er_semestre": 20.0,
      "tiene_ponderacion_paes": true,
      "ponderacion_nem": 10.0,
      "ponderacion_ranking": 50.0,
      "ponderacion_lenguaje": 15.0,
      "ponderacion_matematicas": 10.0,
      "ponderacion_matematicas_2": 0.0,
      "ponderacion_historia": 15.0,
      "ponderacion_ciencias": 15.0,
      "ponderacion_otros": 0.0
    }
  ],
  "indicadores": [
    {
      "institucion": {
        "codigo": 86,
        "nombre": "Pontificia Universidad Católica de Chile",
        "tipo": "Universidades",
        "acreditacion": "Acreditada",
        "tiene_ficha": true
      },
      "nombre_carrera_titulo": "Ciencia Política",
      "empleabilidad_1er_anio": 0.6448598130841121,
      "empleabilidad_2do_anio": 0.7592592592592593,
      "retencion_1er_anio": 0.8222222222222222,
      "continuidad_estudios_pct": 0.12878787878787878,
      "duracion_real_semestres": 11.1627906976744,
      "ingreso_banda_texto": "De $1 millón 500 mil a $1 millón 600 mil"
    },
    {
      "institucion": {
        "codigo": 69,
        "nombre": "Universidad Alberto Hurtado",
        "tipo": "Universidades",
        "acreditacion": "Acreditada",
        "tiene_ficha": true
      },
      "nombre_carrera_titulo": "Ciencia Política y Relaciones Internacionales",
      "empleabilidad_1er_anio": 0.5441176470588235,
      "empleabilidad_2do_anio": null,
      "retencion_1er_anio": 0.7972972972972973,
      "continuidad_estudios_pct": 0.12048192771084337,
      "duracion_real_semestres": 12.0714285714286,
      "ingreso_banda_texto": null
    },
    {
      "institucion": {
        "codigo": 94,
        "nombre": "Universidad Católica de Temuco",
        "tipo": "Universidades",
        "acreditacion": "Acreditada",
        "tiene_ficha": true
      },
      "nombre_carrera_titulo": "Ciencia Política",
      "empleabilidad_1er_anio": 0.4166666666666667,
      "empleabilidad_2do_anio": 0.6666666666666666,
      "retencion_1er_anio": null,
      "continuidad_estudios_pct": 0.044444444444444446,
      "duracion_real_semestres": null,
      "ingreso_banda_texto": null
    },
    {
      "institucion": {
        "codigo": 4,
        "nombre": "Universidad Central de Chile",
        "tipo": "Universidades",
        "acreditacion": "Acreditada",
        "tiene_ficha": true
      },
      "nombre_carrera_titulo": "Ciencia Política",
      "empleabilidad_1er_anio": 0.574468085106383,
      "empleabilidad_2do_anio": 0.7222222222222222,
      "retencion_1er_anio": null,
      "continuidad_estudios_pct": 0.06779661016949153,
      "duracion_real_semestres": 12.075,
      "ingreso_banda_texto": null
    },
    {
      "institucion": {
        "codigo": 84,
        "nombre": "Universidad de Los Lagos",
        "tipo": "Universidades",
        "acreditacion": "Acreditada",
        "tiene_ficha": true
      },
      "nombre_carrera_titulo": "Ciencias Políticas y Administrativas",
      "empleabilidad_1er_anio": 0.56,
      "empleabilidad_2do_anio": null,
      "retencion_1er_anio": null,
      "continuidad_estudios_pct": 0.1,
      "duracion_real_semestres": null,
      "ingreso_banda_texto": "De $1 millón 500 mil a $1 millón 600 mil"
    },
    {
      "institucion": {
        "codigo": 45,
        "nombre": "Universidad del Desarrollo",
        "tipo": "Universidades",
        "acreditacion": "Acreditada",
        "tiene_ficha": true
      },
      "nombre_carrera_titulo": "Ciencias Políticas y Políticas Públicas",
      "empleabilidad_1er_anio": 0.6404494382022472,
      "empleabilidad_2do_anio": 0.8032786885245902,
      "retencion_1er_anio": 0.8378378378378378,
      "continuidad_estudios_pct": 0.09615384615384616,
      "duracion_real_semestres": 11.0344827586207,
      "ingreso_banda_texto": null
    },
    {
      "institucion": {
        "codigo": 3,
        "nombre": "Universidad Diego Portales",
        "tipo": "Universidades",
        "acreditacion": "Acreditada",
        "tiene_ficha": true
      },
      "nombre_carrera_titulo": "Ciencia Política",
      "empleabilidad_1er_anio": 0.5234899328859061,
      "empleabilidad_2do_anio": 0.7111111111111111,
      "retencion_1er_anio": 0.8764044943820225,
      "continuidad_estudios_pct": 0.08620689655172414,
      "duracion_real_semestres": 10.9375,
      "ingreso_banda_texto": "De $1 millón 400 mil a $1 millón 500 mil"
    }
  ]
}