{
  "slug": "comunicacion-audiovisual-y-o-multimedia",
  "nombre": "Comunicación Audiovisual y/o Multimedia",
  "ofertas": [
    {
      "codigo_unico_carrera": "I19S4C5J1V1",
      "institucion": {
        "codigo": 19,
        "nombre": "Universidad de Las Américas",
        "tipo": "Universidades",
        "acreditacion": "Acreditada",
        "tiene_ficha": true
      },
      "nombre_carrera_programa": "COMUNICACION AUDIOVISUAL Y MULTIMEDIA",
      "nivel_carrera": "Profesional",
      "region": "Metropolitana",
      "jornada": "Diurna",
      "sede": "CAMPUS SANTIAGO CENTRO",
      "arancel_anual_2026": "$ 5.800.000",
      "vacantes_1er_semestre": 75.0,
      "tiene_ponderacion_paes": true,
      "ponderacion_nem": 10.0,
      "ponderacion_ranking": 30.0,
      "ponderacion_lenguaje": 25.0,
      "ponderacion_matematicas": 25.0,
      "ponderacion_matematicas_2": 0.0,
      "ponderacion_historia": 10.0,
      "ponderacion_ciencias": 10.0,
      "ponderacion_otros": 0.0
    },
    {
      "codigo_unico_carrera": "I26S1C137J1V3",
      "institucion": {
        "codigo": 26,
        "nombre": "Universidad de Artes, Ciencias y Comunicación UNIACC",
        "tipo": "Universidades",
        "acreditacion": "Acreditada",
        "tiene_ficha": true
      },
      "nombre_carrera_programa": "COMUNICACION AUDIOVISUAL ESPECIALIDAD GUIONES",
      "nivel_carrera": "Profesional",
      "region": "Metropolitana",
      "jornada": "Diurna",
      "sede": "CASA CENTRAL (SANTIAGO)",
      "arancel_anual_2026": "$ 4.590.000",
      "vacantes_1er_semestre": 25.0,
      "tiene_ponderacion_paes": false,
      "ponderacion_nem": 0.0,
      "ponderacion_ranking": 0.0,
      "ponderacion_lenguaje": 0.0,
      "ponderacion_matematicas": 0.0,
      "ponderacion_matematicas_2": 0.0,
      "ponderacion_historia": 0.0,
      "ponderacion_ciencias": 0.0,
      "ponderacion_otros": 0.0
    },
    {
      "codigo_unico_carrera": "I26S1C171J1V3",
      "institucion": {
        "codigo": 26,
        "nombre": "Universidad de Artes, Ciencias y Comunicación UNIACC",
        "tipo": "Universidades",
        "acreditacion": "Acreditada",
        "tiene_ficha": true
      },
      "nombre_carrera_programa": "COMUNICACION DIGITAL ESPECIALIDAD DISEÑO Y DESARROLLO DE VIDEOJUEGOS",
      "nivel_carrera": "Profesional",
      "region": "Metropolitana",
      "jornada": "Diurna",
      "sede": "CASA CENTRAL (SANTIAGO)",
      "arancel_anual_2026": "$ 4.580.000",
      "vacantes_1er_semestre": 50.0,
      "tiene_ponderacion_paes": false,
      "ponderacion_nem": 0.0,
      "ponderacion_ranking": 0.0,
      "ponderacion_lenguaje": 0.0,
      "ponderacion_matematicas": 0.0,
      "ponderacion_matematicas_2": 0.0,
      "ponderacion_historia": 0.0,
      "ponderacion_ciencias": 0.0,
      "ponderacion_otros": 0.0
    },
    {
      "codigo_unico_carrera": "I26S1C52J1V3",
      "institucion": {
        "codigo": 26,
        "nombre": "Universidad de Artes, Ciencias y Comunicación UNIACC",
        "tipo": "Universidades",
        "acreditacion": "Acreditada",
        "tiene_ficha": true
      },
      "nombre_carrera_programa": "COMUNICACION AUDIOVISUAL ESPECIALIDAD TELEVISION",
      "nivel_carrera": "Profesional",
      "region": "Metropolitana",
      "jornada": "Diurna",
      "sede": "CASA CENTRAL (SANTIAGO)",
      "arancel_anual_2026": "$ 4.590.000",
      "vacantes_1er_semestre": 25.0,
      "tiene_ponderacion_paes": false,
      "ponderacion_nem": 0.0,
      "ponderacion_ranking": 0.0,
      "ponderacion_lenguaje": 0.0,
      "ponderacion_matematicas": 0.0,
      "ponderacion_matematicas_2": 0.0,
      "ponderacion_historia": 0.0,
      "ponderacion_ciencias": 0.0,
      "ponderacion_otros": 0.0
    },
    {
      "codigo_unico_carrera": "I26S1C5J1V3",
      "institucion": {
        "codigo": 26,
        "nombre": "Universidad de Artes, Ciencias y Comunicación UNIACC",
        "tipo": "Universidades",
        "acreditacion": "Acreditada",
        "tiene_ficha": true
      },
      "nombre_carrera_programa": "COMUNICACION AUDIOVISUAL ESPECIALIDAD CINE",
      "nivel_carrera": "Profesional",
      "region": "Metropolitana",
      "jornada": "Diurna",
      "sede": "CASA CENTRAL (SANTIAGO)",
      "arancel_anual_2026": "$ 4.590.000",
      "vacantes_1er_semestre": 75.0,
      "tiene_ponderacion_paes": false,
      "ponderacion_nem": 0.0,
      "ponderacion_ranking": 0.0,
      "ponderacion_lenguaje": 0.0,
      "ponderacion_matematicas": 0.0,
      "ponderacion_matematicas_2": 0.0,
      "ponderacion_historia": 0.0,
      "ponderacion_ciencias": 0.0,
      "ponderacion_otros": 0.0
    },
    {
      "codigo_unico_carrera": "I26S1C90J1V3",
      "institucion": {
        "codigo": 26,
        "nombre": "Universidad de Artes, Ciencias y Comunicación UNIACC",
        "tipo": "Universidades",
        "acreditacion": "Acreditada",
        "tiene_ficha": true
      },
      "nombre_carrera_programa": "COMUNICACION DIGITAL ESPECIALIDAD ANIMACION DIGITAL",
      "nivel_carrera": "Profesional",
      "region": "Metropolitana",
      "jornada": "Diurna",
      "sede": "CASA CENTRAL (SANTIAGO)",
      "arancel_anual_2026": "$ 4.580.000",
      "vacantes_1er_semestre": 75.0,
      "tiene_ponderacion_paes": false,
      "ponderacion_nem": 0.0,
      "ponderacion_ranking": 0.0,
      "ponderacion_lenguaje": 0.0,
      "ponderacion_matematicas": 0.0,
      "ponderacion_matematicas_2": 0.0,
      "ponderacion_historia": 0.0,
      "ponderacion_ciencias": 0.0,
      "ponderacion_otros": 0.0
    },
    {
      "codigo_unico_carrera": "I45S4C1218J1V1",
      "institucion": {
        "codigo": 45,
        "nombre": "Universidad del Desarrollo",
        "tipo": "Universidades",
        "acreditacion": "Acreditada",
        "tiene_ficha": true
      },
      "nombre_carrera_programa": "LICENCIATURA EN COMUNICACION AUDIOVISUAL",
      "nivel_carrera": "Profesional",
      "region": "Metropolitana",
      "jornada": "Diurna",
      "sede": "SEDE SANTIAGO (S.C. APOQUINDO)",
      "arancel_anual_2026": "UF 221",
      "vacantes_1er_semestre": 50.0,
      "tiene_ponderacion_paes": false,
      "ponderacion_nem": 0.0,
      "ponderacion_ranking": 0.0,
      "ponderacion_lenguaje": 0.0,
      "ponderacion_matematicas": 0.0,
      "ponderacion_matematicas_2": 0.0,
      "ponderacion_historia": 0.0,
      "ponderacion_ciencias": 0.0,
      "ponderacion_otros": 0.0
    },
    {
      "codigo_unico_carrera": "I93S1C255J1V2",
      "institucion": {
        "codigo": 93,
        "nombre": "Universidad Católica de la Santísima Concepción",
        "tipo": "Universidades",
        "acreditacion": "Acreditada",
        "tiene_ficha": true
      },
      "nombre_carrera_programa": "DIRECCION AUDIOVISUAL Y MULTIMEDIA",
      "nivel_carrera": "Profesional",
      "region": "Biobío",
      "jornada": "Diurna",
      "sede": "CASA CENTRAL (CONCEPCION)",
      "arancel_anual_2026": "$ 5.070.000",
      "vacantes_1er_semestre": 45.0,
      "tiene_ponderacion_paes": true,
      "ponderacion_nem": 20.0,
      "ponderacion_ranking": 40.0,
      "ponderacion_lenguaje": 20.0,
      "ponderacion_matematicas": 10.0,
      "ponderacion_matematicas_2": 0.0,
      "ponderacion_historia": 10.0,
      "ponderacion_ciencias": 10.0,
      "ponderacion_otros": 0.0
    },
    {
      "codigo_unico_carrera": "I111S3C38J1V1",
      "institucion": {
        "codigo": 111,
        "nombre": "Instituto Profesional Duoc UC",
        "tipo": "Institutos Profesionales",
        "acreditacion": "Acreditada",
        "tiene_ficha": true
      },
      "nombre_carrera_programa": "COMUNICACION AUDIOVISUAL",
      "nivel_carrera": "Profesional",
      "region": "Biobío",
      "jornada": "Diurna",
      "sede": "SEDE CONCEPCION",
      "arancel_anual_2026": "$ 3.530.000",
      "vacantes_1er_semestre": 80.0,
      "tiene_ponderacion_paes": false,
      "ponderacion_nem": 0.0,
      "ponderacion_ranking": 0.0,
      "ponderacion_lenguaje": 0.0,
      "ponderacion_matematicas": 0.0,
      "ponderacion_matematicas_2": 0.0,
      "ponderacion_historia": 0.0,
      "ponderacion_ciencias": 0.0,
      "ponderacion_otros": 0.0
    },
    {
      "codigo_unico_carrera": "I111S4C38J1V1",
      "institucion": {
        "codigo": 111,
        "nombre": "Instituto Profesional Duoc UC",
        "tipo": "Institutos Profesionales",
        "acreditacion": "Acreditada",
        "tiene_ficha": true
      },
      "nombre_carrera_programa": "COMUNICACION AUDIOVISUAL",
      "nivel_carrera": "Profesional",
      "region": "Valparaíso",
      "jornada": "Diurna",
      "sede": "SEDE VIÑA DEL MAR",
      "arancel_anual_2026": "$ 3.990.000",
      "vacantes_1er_semestre": 115.0,
      "tiene_ponderacion_paes": false,
      "ponderacion_nem": 0.0,
      "ponderacion_ranking": 0.0,
      "ponderacion_lenguaje": 0.0,
      "ponderacion_matematicas": 0.0,
      "ponderacion_matematicas_2": 0.0,
      "ponderacion_historia": 0.0,
      "ponderacion_ciencias": 0.0,
      "ponderacion_otros": 0.0
    },
    {
      "codigo_unico_carrera": "I111S6C38J1V1",
      "institucion": {
        "codigo": 111,
        "nombre": "Instituto Profesional Duoc UC",
        "tipo": "Institutos Profesionales",
        "acreditacion": "Acreditada",
        "tiene_ficha": true
      },
      "nombre_carrera_programa": "COMUNICACION AUDIOVISUAL",
      "nivel_carrera": "Profesional",
      "region": "Metropolitana",
      "jornada": "Diurna",
      "sede": "SEDE SAN CARLOS DE APOQUINDO",
      "arancel_anual_2026": "$ 4.380.000",
      "vacantes_1er_semestre": 160.0,
      "tiene_ponderacion_paes": false,
      "ponderacion_nem": 0.0,
      "ponderacion_ranking": 0.0,
      "ponderacion_lenguaje": 0.0,
      "ponderacion_matematicas": 0.0,
      "ponderacion_matematicas_2": 0.0,
      "ponderacion_historia": 0.0,
      "ponderacion_ciencias": 0.0,
      "ponderacion_otros": 0.0
    },
    {
      "codigo_unico_carrera": "I116S34C46J1V1",
      "institucion": {
        "codigo": 116,
        "nombre": "Instituto Profesional Santo Tomás",
        "tipo": "Institutos Profesionales",
        "acreditacion": "Acreditada",
        "tiene_ficha": true
      },
      "nombre_carrera_programa": "COMUNICACION AUDIOVISUAL DIGITAL",
      "nivel_carrera": "Profesional",
      "region": "Biobío",
      "jornada": "Diurna",
      "sede": "SEDE CONCEPCION",
      "arancel_anual_2026": "$ 3.393.000",
      "vacantes_1er_semestre": 70.0,
      "tiene_ponderacion_paes": false,
      "ponderacion_nem": 0.0,
      "ponderacion_ranking": 0.0,
      "ponderacion_lenguaje": 0.0,
      "ponderacion_matematicas": 0.0,
      "ponderacion_matematicas_2": 0.0,
      "ponderacion_historia": 0.0,
      "ponderacion_ciencias": 0.0,
      "ponderacion_otros": 0.0
    },
    {
      "codigo_unico_carrera": "I116S39C46J1V1",
      "institucion": {
        "codigo": 116,
        "nombre": "Instituto Profesional Santo Tomás",
        "tipo": "Institutos Profesionales",
        "acreditacion": "Acreditada",
        "tiene_ficha": true
      },
      "nombre_carrera_programa": "COMUNICACION AUDIOVISUAL DIGITAL",
      "nivel_carrera": "Profesional",
      "region": "Metropolitana",
      "jornada": "Diurna",
      "sede": "SEDE SAN JOAQUIN",
      "arancel_anual_2026": "$ 3.916.000",
      "vacantes_1er_semestre": 150.0,
      "tiene_ponderacion_paes": false,
      "ponderacion_nem": 0.0,
      "ponderacion_ranking": 0.0,
      "ponderacion_lenguaje": 0.0,
      "ponderacion_matematicas": 0.0,
      "ponderacion_matematicas_2": 0.0,
      "ponderacion_historia": 0.0,
      "ponderacion_ciencias": 0.0,
      "ponderacion_otros": 0.0
    },
    {
      "codigo_unico_carrera": "I116S6C46J1V1",
      "institucion": {
        "codigo": 116,
        "nombre": "Instituto Profesional Santo Tomás",
        "tipo": "Institutos Profesionales",
        "acreditacion": "Acreditada",
        "tiene_ficha": true
      },
      "nombre_carrera_programa": "COMUNICACION AUDIOVISUAL DIGITAL",
      "nivel_carrera": "Profesional",
      "region": "Maule",
      "jornada": "Diurna",
      "sede": "SEDE TALCA",
      "arancel_anual_2026": "$ 3.935.000",
      "vacantes_1er_semestre": 85.0,
      "tiene_ponderacion_paes": false,
      "ponderacion_nem": 0.0,
      "ponderacion_ranking": 0.0,
      "ponderacion_lenguaje": 0.0,
      "ponderacion_matematicas": 0.0,
      "ponderacion_matematicas_2": 0.0,
      "ponderacion_historia": 0.0,
      "ponderacion_ciencias": 0.0,
      "ponderacion_otros": 0.0
    },
    {
      "codigo_unico_carrera": "I123S2C7J1V1",
      "institucion": {
        "codigo": 123,
        "nombre": "Instituto Profesional de Chile",
        "tipo": "Institutos Profesionales",
        "acreditacion": "Acreditada",
        "tiene_ficha": true
      },
      "nombre_carrera_programa": "COMUNICACION AUDIOVISUAL",
      "nivel_carrera": "Profesional",
      "region": "Metropolitana",
      "jornada": "Diurna",
      "sede": "CASA CENTRAL (SANTIAGO)",
      "arancel_anual_2026": "$ 2.062.000",
      "vacantes_1er_semestre": 50.0,
      "tiene_ponderacion_paes": false,
      "ponderacion_nem": 0.0,
      "ponderacion_ranking": 0.0,
      "ponderacion_lenguaje": 0.0,
      "ponderacion_matematicas": 0.0,
      "ponderacion_matematicas_2": 0.0,
      "ponderacion_historia": 0.0,
      "ponderacion_ciencias": 0.0,
      "ponderacion_otros": 0.0
    },
    {
      "codigo_unico_carrera": "I123S2C7J4V3",
      "institucion": {
        "codigo": 123,
        "nombre": "Instituto Profesional de Chile",
        "tipo": "Institutos Profesionales",
        "acreditacion": "Acreditada",
        "tiene_ficha": true
      },
      "nombre_carrera_programa": "COMUNICACION AUDIOVISUAL",
      "nivel_carrera": "Profesional",
      "region": "Metropolitana",
      "jornada": "A Distancia",
      "sede": "CASA CENTRAL (SANTIAGO)",
      "arancel_anual_2026": "$ 1.650.000",
      "vacantes_1er_semestre": 22.0,
      "tiene_ponderacion_paes": false,
      "ponderacion_nem": 0.0,
      "ponderacion_ranking": 0.0,
      "ponderacion_lenguaje": 0.0,
      "ponderacion_matematicas": 0.0,
      "ponderacion_matematicas_2": 0.0,
      "ponderacion_historia": 0.0,
      "ponderacion_ciencias": 0.0,
      "ponderacion_otros": 0.0
    }
  ],
  "indicadores": [
    {
      "institucion": {
        "codigo": 144,
        "nombre": "Instituto Profesional ARCOS",
        "tipo": "Institutos Profesionales",
        "acreditacion": "No Acreditada",
        "tiene_ficha": true
      },
      "nombre_carrera_titulo": "Comunicación Audiovisual",
      "empleabilidad_1er_anio": 0.32608695652173914,
      "empleabilidad_2do_anio": null,
      "retencion_1er_anio": 0.4482758620689655,
      "continuidad_estudios_pct": 0.06611570247933884,
      "duracion_real_semestres": 8.89473684210526,
      "ingreso_banda_texto": null
    },
    {
      "institucion": {
        "codigo": 123,
        "nombre": "Instituto Profesional de Chile",
        "tipo": "Institutos Profesionales",
        "acreditacion": "Acreditada",
        "tiene_ficha": true
      },
      "nombre_carrera_titulo": "Comunicación Audiovisual",
      "empleabilidad_1er_anio": 0.5915492957746479,
      "empleabilidad_2do_anio": 0.6805555555555556,
      "retencion_1er_anio": 0.7647058823529411,
      "continuidad_estudios_pct": 0.047058823529411764,
      "duracion_real_semestres": null,
      "ingreso_banda_texto": null
    },
    {
      "institucion": {
        "codigo": 111,
        "nombre": "Instituto Profesional Duoc UC",
        "tipo": "Institutos Profesionales",
        "acreditacion": "Acreditada",
        "tiene_ficha": true
      },
      "nombre_carrera_titulo": "Comunicación Audiovisual",
      "empleabilidad_1er_anio": 0.47491638795986624,
      "empleabilidad_2do_anio": 0.5623762376237624,
      "retencion_1er_anio": 0.8461538461538461,
      "continuidad_estudios_pct": 0.024965325936199722,
      "duracion_real_semestres": 9.52,
      "ingreso_banda_texto": "De $900 mil a $1 millón"
    },
    {
      "institucion": {
        "codigo": 116,
        "nombre": "Instituto Profesional Santo Tomás",
        "tipo": "Institutos Profesionales",
        "acreditacion": "Acreditada",
        "tiene_ficha": true
      },
      "nombre_carrera_titulo": "Comunicación Audiovisual Digital",
      "empleabilidad_1er_anio": 0.45714285714285713,
      "empleabilidad_2do_anio": 0.5673469387755102,
      "retencion_1er_anio": 0.8458781362007168,
      "continuidad_estudios_pct": 0.029315960912052116,
      "duracion_real_semestres": 9.294736842105264,
      "ingreso_banda_texto": "De $1 millón a $1 millón 100 mil"
    },
    {
      "institucion": {
        "codigo": 86,
        "nombre": "Pontificia Universidad Católica de Chile",
        "tipo": "Universidades",
        "acreditacion": "Acreditada",
        "tiene_ficha": true
      },
      "nombre_carrera_titulo": "Dirección Audiovisual",
      "empleabilidad_1er_anio": 0.5684210526315789,
      "empleabilidad_2do_anio": 0.6236559139784946,
      "retencion_1er_anio": null,
      "continuidad_estudios_pct": 0.009345794392523364,
      "duracion_real_semestres": 12.0666666666667,
      "ingreso_banda_texto": "De $1 millón 300 mil a $1 millón 400 mil"
    },
    {
      "institucion": {
        "codigo": 93,
        "nombre": "Universidad Católica de la Santísima Concepción",
        "tipo": "Universidades",
        "acreditacion": "Acreditada",
        "tiene_ficha": true
      },
      "nombre_carrera_titulo": "Dirección Audiovisual y Multimedia",
      "empleabilidad_1er_anio": 0.23684210526315788,
      "empleabilidad_2do_anio": 0.43859649122807015,
      "retencion_1er_anio": 0.8947368421052632,
      "continuidad_estudios_pct": 0.014388489208633094,
      "duracion_real_semestres": 9.11764705882353,
      "ingreso_banda_texto": null
    },
    {
      "institucion": {
        "codigo": 26,
        "nombre": "Universidad de Artes, Ciencias y Comunicación UNIACC",
        "tipo": "Universidades",
        "acreditacion": "Acreditada",
        "tiene_ficha": true
      },
      "nombre_carrera_titulo": "Comunicación Audiovisual y Digital",
      "empleabilidad_1er_anio": 0.5217391304347826,
      "empleabilidad_2do_anio": 0.552,
      "retencion_1er_anio": 0.7939698492462312,
      "continuidad_estudios_pct": 0.03365384615384615,
      "duracion_real_semestres": 12.726027397260289,
      "ingreso_banda_texto": "De $1 millón 200 mil a $1 millón 300 mil"
    },
    {
      "institucion": {
        "codigo": 34,
        "nombre": "Universidad de Los Andes",
        "tipo": "Universidades",
        "acreditacion": "Acreditada",
        "tiene_ficha": true
      },
      "nombre_carrera_titulo": "Comunicación Audiovisual",
      "empleabilidad_1er_anio": 0.5806451612903226,
      "empleabilidad_2do_anio": null,
      "retencion_1er_anio": null,
      "continuidad_estudios_pct": 0.0,
      "duracion_real_semestres": null,
      "ingreso_banda_texto": null
    }
  ]
}