{
  "slug": "traduccion-e-interpretacion",
  "nombre": "Traducción e Interpretación",
  "ofertas": [
    {
      "codigo_unico_carrera": "I19S1C62J1V2",
      "institucion": {
        "codigo": 19,
        "nombre": "Universidad de Las Américas",
        "tipo": "Universidades",
        "acreditacion": "Acreditada",
        "tiene_ficha": true
      },
      "nombre_carrera_programa": "TRADUCCION E INTERPRETACION EN INGLES",
      "nivel_carrera": "Profesional",
      "region": "Metropolitana",
      "jornada": "Diurna",
      "sede": "CAMPUS PROVIDENCIA",
      "arancel_anual_2026": "$ 5.100.000",
      "vacantes_1er_semestre": 165.0,
      "tiene_ponderacion_paes": true,
      "ponderacion_nem": 10.0,
      "ponderacion_ranking": 30.0,
      "ponderacion_lenguaje": 25.0,
      "ponderacion_matematicas": 25.0,
      "ponderacion_matematicas_2": 0.0,
      "ponderacion_historia": 10.0,
      "ponderacion_ciencias": 10.0,
      "ponderacion_otros": 0.0
    },
    {
      "codigo_unico_carrera": "I19S5C62J1V2",
      "institucion": {
        "codigo": 19,
        "nombre": "Universidad de Las Américas",
        "tipo": "Universidades",
        "acreditacion": "Acreditada",
        "tiene_ficha": true
      },
      "nombre_carrera_programa": "TRADUCCION E INTERPRETACION EN INGLES",
      "nivel_carrera": "Profesional",
      "region": "Biobío",
      "jornada": "Diurna",
      "sede": "SEDE CONCEPCION",
      "arancel_anual_2026": "$ 4.620.000",
      "vacantes_1er_semestre": 50.0,
      "tiene_ponderacion_paes": true,
      "ponderacion_nem": 10.0,
      "ponderacion_ranking": 30.0,
      "ponderacion_lenguaje": 25.0,
      "ponderacion_matematicas": 25.0,
      "ponderacion_matematicas_2": 0.0,
      "ponderacion_historia": 10.0,
      "ponderacion_ciencias": 10.0,
      "ponderacion_otros": 0.0
    },
    {
      "codigo_unico_carrera": "I19S6C62J1V2",
      "institucion": {
        "codigo": 19,
        "nombre": "Universidad de Las Américas",
        "tipo": "Universidades",
        "acreditacion": "Acreditada",
        "tiene_ficha": true
      },
      "nombre_carrera_programa": "TRADUCCION E INTERPRETACION EN INGLES",
      "nivel_carrera": "Profesional",
      "region": "Valparaíso",
      "jornada": "Diurna",
      "sede": "SEDE VIÑA DEL MAR",
      "arancel_anual_2026": "$ 4.730.000",
      "vacantes_1er_semestre": 43.0,
      "tiene_ponderacion_paes": true,
      "ponderacion_nem": 15.0,
      "ponderacion_ranking": 35.0,
      "ponderacion_lenguaje": 30.0,
      "ponderacion_matematicas": 10.0,
      "ponderacion_matematicas_2": 0.0,
      "ponderacion_historia": 10.0,
      "ponderacion_ciencias": 10.0,
      "ponderacion_otros": 0.0
    },
    {
      "codigo_unico_carrera": "I26S1C32J1V2",
      "institucion": {
        "codigo": 26,
        "nombre": "Universidad de Artes, Ciencias y Comunicación UNIACC",
        "tipo": "Universidades",
        "acreditacion": "Acreditada",
        "tiene_ficha": true
      },
      "nombre_carrera_programa": "TRADUCCION E INTERPRETARIADO BILINGÜE INGLES-ESPAÑOL",
      "nivel_carrera": "Profesional",
      "region": "Metropolitana",
      "jornada": "Diurna",
      "sede": "CASA CENTRAL (SANTIAGO)",
      "arancel_anual_2026": "$ 3.800.000",
      "vacantes_1er_semestre": 110.0,
      "tiene_ponderacion_paes": false,
      "ponderacion_nem": 0.0,
      "ponderacion_ranking": 0.0,
      "ponderacion_lenguaje": 0.0,
      "ponderacion_matematicas": 0.0,
      "ponderacion_matematicas_2": 0.0,
      "ponderacion_historia": 0.0,
      "ponderacion_ciencias": 0.0,
      "ponderacion_otros": 0.0
    },
    {
      "codigo_unico_carrera": "I74S1C63J1V1",
      "institucion": {
        "codigo": 74,
        "nombre": "Universidad de La Serena",
        "tipo": "Universidades",
        "acreditacion": "Acreditada",
        "tiene_ficha": true
      },
      "nombre_carrera_programa": "TRADUCCION INGLES ESPAÑOL",
      "nivel_carrera": "Profesional",
      "region": "Coquimbo",
      "jornada": "Diurna",
      "sede": "LA SERENA",
      "arancel_anual_2026": "$ 3.637.000",
      "vacantes_1er_semestre": 30.0,
      "tiene_ponderacion_paes": true,
      "ponderacion_nem": 20.0,
      "ponderacion_ranking": 20.0,
      "ponderacion_lenguaje": 40.0,
      "ponderacion_matematicas": 10.0,
      "ponderacion_matematicas_2": 0.0,
      "ponderacion_historia": 10.0,
      "ponderacion_ciencias": 0.0,
      "ponderacion_otros": 0.0
    },
    {
      "codigo_unico_carrera": "I79S1C229J1V1",
      "institucion": {
        "codigo": 79,
        "nombre": "Universidad de Atacama",
        "tipo": "Universidades",
        "acreditacion": "Acreditación Extendida",
        "tiene_ficha": true
      },
      "nombre_carrera_programa": "LICENCIATURA EN TRADUCTOLOGIA Y TRADUCTOR E INTERPRETE INGLES-ESPAÑOL",
      "nivel_carrera": "Profesional",
      "region": "Atacama",
      "jornada": "Diurna",
      "sede": "CASA CENTRAL (COPIAPO)",
      "arancel_anual_2026": "$ 3.524.000",
      "vacantes_1er_semestre": 37.0,
      "tiene_ponderacion_paes": true,
      "ponderacion_nem": 10.0,
      "ponderacion_ranking": 40.0,
      "ponderacion_lenguaje": 20.0,
      "ponderacion_matematicas": 20.0,
      "ponderacion_matematicas_2": 0.0,
      "ponderacion_historia": 10.0,
      "ponderacion_ciencias": 0.0,
      "ponderacion_otros": 0.0
    },
    {
      "codigo_unico_carrera": "I81S1C496J1V1",
      "institucion": {
        "codigo": 81,
        "nombre": "Universidad Arturo Prat",
        "tipo": "Universidades",
        "acreditacion": "Acreditada",
        "tiene_ficha": true
      },
      "nombre_carrera_programa": "TRADUCCION INGLES CASTELLANO INGLES MENCION FRANCES",
      "nivel_carrera": "Profesional",
      "region": "Tarapacá",
      "jornada": "Diurna",
      "sede": "CASA CENTRAL (IQUIQUE)",
      "arancel_anual_2026": "$ 3.673.000",
      "vacantes_1er_semestre": 30.0,
      "tiene_ponderacion_paes": true,
      "ponderacion_nem": 10.0,
      "ponderacion_ranking": 40.0,
      "ponderacion_lenguaje": 30.0,
      "ponderacion_matematicas": 10.0,
      "ponderacion_matematicas_2": 0.0,
      "ponderacion_historia": 10.0,
      "ponderacion_ciencias": 10.0,
      "ponderacion_otros": 0.0
    },
    {
      "codigo_unico_carrera": "I83S1C68J1V1",
      "institucion": {
        "codigo": 83,
        "nombre": "Universidad de Playa Ancha de Ciencias de la Educación",
        "tipo": "Universidades",
        "acreditacion": "Acreditada",
        "tiene_ficha": true
      },
      "nombre_carrera_programa": "TRADUCCION E INTERPRETACION INGLES-ESPAÑOL",
      "nivel_carrera": "Profesional",
      "region": "Valparaíso",
      "jornada": "Diurna",
      "sede": "CASA CENTRAL (VALPARAISO)",
      "arancel_anual_2026": "$ 4.165.000",
      "vacantes_1er_semestre": 30.0,
      "tiene_ponderacion_paes": true,
      "ponderacion_nem": 30.0,
      "ponderacion_ranking": 30.0,
      "ponderacion_lenguaje": 20.0,
      "ponderacion_matematicas": 10.0,
      "ponderacion_matematicas_2": 0.0,
      "ponderacion_historia": 10.0,
      "ponderacion_ciencias": 10.0,
      "ponderacion_otros": 0.0
    },
    {
      "codigo_unico_carrera": "I87S1C237J1V1",
      "institucion": {
        "codigo": 87,
        "nombre": "Universidad de Concepción",
        "tipo": "Universidades",
        "acreditacion": "Acreditada",
        "tiene_ficha": true
      },
      "nombre_carrera_programa": "TRADUCCION/INTERPRETACION EN IDIOMAS EXTRANJEROS",
      "nivel_carrera": "Profesional",
      "region": "Biobío",
      "jornada": "Diurna",
      "sede": "CASA CENTRAL",
      "arancel_anual_2026": "$ 7.110.522",
      "vacantes_1er_semestre": 73.0,
      "tiene_ponderacion_paes": true,
      "ponderacion_nem": 15.0,
      "ponderacion_ranking": 25.0,
      "ponderacion_lenguaje": 25.0,
      "ponderacion_matematicas": 25.0,
      "ponderacion_matematicas_2": 0.0,
      "ponderacion_historia": 10.0,
      "ponderacion_ciencias": 0.0,
      "ponderacion_otros": 0.0
    },
    {
      "codigo_unico_carrera": "I89S3C51J1V2",
      "institucion": {
        "codigo": 89,
        "nombre": "Pontificia Universidad Católica de Valparaíso",
        "tipo": "Universidades",
        "acreditacion": "Acreditada",
        "tiene_ficha": true
      },
      "nombre_carrera_programa": "INTERPRETACION O TRADUCCION INGLES-ESPAÑOL (PLAN COMUN)",
      "nivel_carrera": "Profesional",
      "region": "Valparaíso",
      "jornada": "Diurna",
      "sede": "VIÑA DEL MAR",
      "arancel_anual_2026": "$ 5.350.000",
      "vacantes_1er_semestre": 65.0,
      "tiene_ponderacion_paes": true,
      "ponderacion_nem": 20.0,
      "ponderacion_ranking": 20.0,
      "ponderacion_lenguaje": 30.0,
      "ponderacion_matematicas": 20.0,
      "ponderacion_matematicas_2": 0.0,
      "ponderacion_historia": 10.0,
      "ponderacion_ciencias": 10.0,
      "ponderacion_otros": 0.0
    },
    {
      "codigo_unico_carrera": "I89S3C573J1V1",
      "institucion": {
        "codigo": 89,
        "nombre": "Pontificia Universidad Católica de Valparaíso",
        "tipo": "Universidades",
        "acreditacion": "Acreditada",
        "tiene_ficha": true
      },
      "nombre_carrera_programa": "INTERPRETACION INGLES-ESPAÑOL",
      "nivel_carrera": "Profesional",
      "region": "Valparaíso",
      "jornada": "Diurna",
      "sede": "VIÑA DEL MAR",
      "arancel_anual_2026": "$ 5.350.000",
      "vacantes_1er_semestre": 65.0,
      "tiene_ponderacion_paes": false,
      "ponderacion_nem": 0.0,
      "ponderacion_ranking": 0.0,
      "ponderacion_lenguaje": 0.0,
      "ponderacion_matematicas": 0.0,
      "ponderacion_matematicas_2": 0.0,
      "ponderacion_historia": 0.0,
      "ponderacion_ciencias": 0.0,
      "ponderacion_otros": 0.0
    },
    {
      "codigo_unico_carrera": "I89S3C575J1V1",
      "institucion": {
        "codigo": 89,
        "nombre": "Pontificia Universidad Católica de Valparaíso",
        "tipo": "Universidades",
        "acreditacion": "Acreditada",
        "tiene_ficha": true
      },
      "nombre_carrera_programa": "TRADUCCION INGLES-ESPAÑOL",
      "nivel_carrera": "Profesional",
      "region": "Valparaíso",
      "jornada": "Diurna",
      "sede": "VIÑA DEL MAR",
      "arancel_anual_2026": "$ 5.350.000",
      "vacantes_1er_semestre": 65.0,
      "tiene_ponderacion_paes": false,
      "ponderacion_nem": 0.0,
      "ponderacion_ranking": 0.0,
      "ponderacion_lenguaje": 0.0,
      "ponderacion_matematicas": 0.0,
      "ponderacion_matematicas_2": 0.0,
      "ponderacion_historia": 0.0,
      "ponderacion_ciencias": 0.0,
      "ponderacion_otros": 0.0
    },
    {
      "codigo_unico_carrera": "I94S1C29J1V1",
      "institucion": {
        "codigo": 94,
        "nombre": "Universidad Católica de Temuco",
        "tipo": "Universidades",
        "acreditacion": "Acreditada",
        "tiene_ficha": true
      },
      "nombre_carrera_programa": "TRADUCCION INGLES-ESPAÑOL",
      "nivel_carrera": "Profesional",
      "region": "La Araucanía",
      "jornada": "Diurna",
      "sede": "CASA CENTRAL (TEMUCO)",
      "arancel_anual_2026": "$ 5.276.000",
      "vacantes_1er_semestre": 46.0,
      "tiene_ponderacion_paes": true,
      "ponderacion_nem": 10.0,
      "ponderacion_ranking": 50.0,
      "ponderacion_lenguaje": 15.0,
      "ponderacion_matematicas": 15.0,
      "ponderacion_matematicas_2": 0.0,
      "ponderacion_historia": 10.0,
      "ponderacion_ciencias": 10.0,
      "ponderacion_otros": 0.0
    },
    {
      "codigo_unico_carrera": "I108S1C23J1V1",
      "institucion": {
        "codigo": 108,
        "nombre": "Instituto Profesional Chileno Británico de Cultura",
        "tipo": "Institutos Profesionales",
        "acreditacion": "No Acreditada",
        "tiene_ficha": true
      },
      "nombre_carrera_programa": "TRADUCCION PROFESIONAL DEL INGLES AL ESPAÑOL",
      "nivel_carrera": "Profesional",
      "region": "Metropolitana",
      "jornada": "Diurna",
      "sede": "CASA CENTRAL (SANTIAGO)",
      "arancel_anual_2026": "$ 2.570.000",
      "vacantes_1er_semestre": 30.0,
      "tiene_ponderacion_paes": false,
      "ponderacion_nem": 0.0,
      "ponderacion_ranking": 0.0,
      "ponderacion_lenguaje": 0.0,
      "ponderacion_matematicas": 0.0,
      "ponderacion_matematicas_2": 0.0,
      "ponderacion_historia": 0.0,
      "ponderacion_ciencias": 0.0,
      "ponderacion_otros": 0.0
    },
    {
      "codigo_unico_carrera": "I108S1C23J2V2",
      "institucion": {
        "codigo": 108,
        "nombre": "Instituto Profesional Chileno Británico de Cultura",
        "tipo": "Institutos Profesionales",
        "acreditacion": "No Acreditada",
        "tiene_ficha": true
      },
      "nombre_carrera_programa": "TRADUCCION PROFESIONAL DEL INGLES AL ESPAÑOL",
      "nivel_carrera": "Profesional",
      "region": "Metropolitana",
      "jornada": "Vespertina",
      "sede": "CASA CENTRAL (SANTIAGO)",
      "arancel_anual_2026": "$ 2.520.000",
      "vacantes_1er_semestre": 20.0,
      "tiene_ponderacion_paes": false,
      "ponderacion_nem": 0.0,
      "ponderacion_ranking": 0.0,
      "ponderacion_lenguaje": 0.0,
      "ponderacion_matematicas": 0.0,
      "ponderacion_matematicas_2": 0.0,
      "ponderacion_historia": 0.0,
      "ponderacion_ciencias": 0.0,
      "ponderacion_otros": 0.0
    },
    {
      "codigo_unico_carrera": "I108S1C23J4V1",
      "institucion": {
        "codigo": 108,
        "nombre": "Instituto Profesional Chileno Británico de Cultura",
        "tipo": "Institutos Profesionales",
        "acreditacion": "No Acreditada",
        "tiene_ficha": true
      },
      "nombre_carrera_programa": "TRADUCCION PROFESIONAL DEL INGLES AL ESPAÑOL A DISTANCIA",
      "nivel_carrera": "Profesional",
      "region": "Metropolitana",
      "jornada": "A Distancia",
      "sede": "CASA CENTRAL (SANTIAGO)",
      "arancel_anual_2026": "$ 2.415.000",
      "vacantes_1er_semestre": 10.0,
      "tiene_ponderacion_paes": false,
      "ponderacion_nem": 0.0,
      "ponderacion_ranking": 0.0,
      "ponderacion_lenguaje": 0.0,
      "ponderacion_matematicas": 0.0,
      "ponderacion_matematicas_2": 0.0,
      "ponderacion_historia": 0.0,
      "ponderacion_ciencias": 0.0,
      "ponderacion_otros": 0.0
    },
    {
      "codigo_unico_carrera": "I108S1C28J1V1",
      "institucion": {
        "codigo": 108,
        "nombre": "Instituto Profesional Chileno Británico de Cultura",
        "tipo": "Institutos Profesionales",
        "acreditacion": "No Acreditada",
        "tiene_ficha": true
      },
      "nombre_carrera_programa": "INTERPRETACION PROFESIONAL DEL INGLES AL ESPAÑOL",
      "nivel_carrera": "Profesional",
      "region": "Metropolitana",
      "jornada": "Diurna",
      "sede": "CASA CENTRAL (SANTIAGO)",
      "arancel_anual_2026": "$ 2.570.000",
      "vacantes_1er_semestre": 25.0,
      "tiene_ponderacion_paes": false,
      "ponderacion_nem": 0.0,
      "ponderacion_ranking": 0.0,
      "ponderacion_lenguaje": 0.0,
      "ponderacion_matematicas": 0.0,
      "ponderacion_matematicas_2": 0.0,
      "ponderacion_historia": 0.0,
      "ponderacion_ciencias": 0.0,
      "ponderacion_otros": 0.0
    },
    {
      "codigo_unico_carrera": "I108S1C28J2V1",
      "institucion": {
        "codigo": 108,
        "nombre": "Instituto Profesional Chileno Británico de Cultura",
        "tipo": "Institutos Profesionales",
        "acreditacion": "No Acreditada",
        "tiene_ficha": true
      },
      "nombre_carrera_programa": "INTERPRETACION PROFESIONAL DEL INGLES AL ESPAÑOL",
      "nivel_carrera": "Profesional",
      "region": "Metropolitana",
      "jornada": "Vespertina",
      "sede": "CASA CENTRAL (SANTIAGO)",
      "arancel_anual_2026": "$ 2.520.000",
      "vacantes_1er_semestre": 20.0,
      "tiene_ponderacion_paes": false,
      "ponderacion_nem": 0.0,
      "ponderacion_ranking": 0.0,
      "ponderacion_lenguaje": 0.0,
      "ponderacion_matematicas": 0.0,
      "ponderacion_matematicas_2": 0.0,
      "ponderacion_historia": 0.0,
      "ponderacion_ciencias": 0.0,
      "ponderacion_otros": 0.0
    },
    {
      "codigo_unico_carrera": "I108S1C28J4V1",
      "institucion": {
        "codigo": 108,
        "nombre": "Instituto Profesional Chileno Británico de Cultura",
        "tipo": "Institutos Profesionales",
        "acreditacion": "No Acreditada",
        "tiene_ficha": true
      },
      "nombre_carrera_programa": "INTERPRETACION PROFESIONAL DEL INGLES AL ESPAÑOL A DISTANCIA",
      "nivel_carrera": "Profesional",
      "region": "Metropolitana",
      "jornada": "A Distancia",
      "sede": "CASA CENTRAL (SANTIAGO)",
      "arancel_anual_2026": "$ 2.415.000",
      "vacantes_1er_semestre": 40.0,
      "tiene_ponderacion_paes": false,
      "ponderacion_nem": 0.0,
      "ponderacion_ranking": 0.0,
      "ponderacion_lenguaje": 0.0,
      "ponderacion_matematicas": 0.0,
      "ponderacion_matematicas_2": 0.0,
      "ponderacion_historia": 0.0,
      "ponderacion_ciencias": 0.0,
      "ponderacion_otros": 0.0
    },
    {
      "codigo_unico_carrera": "I137S1C40J1V1",
      "institucion": {
        "codigo": 137,
        "nombre": "Instituto Profesional EATRI",
        "tipo": "Institutos Profesionales",
        "acreditacion": "Acreditación Extendida",
        "tiene_ficha": true
      },
      "nombre_carrera_programa": "TRADUCCION INGLES ESPAÑOL INGLES",
      "nivel_carrera": "Profesional",
      "region": "Metropolitana",
      "jornada": "Diurna",
      "sede": "CASA CENTRAL",
      "arancel_anual_2026": "$ 2.610.000",
      "vacantes_1er_semestre": 27.0,
      "tiene_ponderacion_paes": false,
      "ponderacion_nem": 0.0,
      "ponderacion_ranking": 0.0,
      "ponderacion_lenguaje": 0.0,
      "ponderacion_matematicas": 0.0,
      "ponderacion_matematicas_2": 0.0,
      "ponderacion_historia": 0.0,
      "ponderacion_ciencias": 0.0,
      "ponderacion_otros": 0.0
    },
    {
      "codigo_unico_carrera": "I137S1C40J4V1",
      "institucion": {
        "codigo": 137,
        "nombre": "Instituto Profesional EATRI",
        "tipo": "Institutos Profesionales",
        "acreditacion": "Acreditación Extendida",
        "tiene_ficha": true
      },
      "nombre_carrera_programa": "TRADUCCION INGLES ESPAÑOL INGLES",
      "nivel_carrera": "Profesional",
      "region": "Metropolitana",
      "jornada": "A Distancia",
      "sede": "CASA CENTRAL",
      "arancel_anual_2026": "$ 2.610.000",
      "vacantes_1er_semestre": 75.0,
      "tiene_ponderacion_paes": false,
      "ponderacion_nem": 0.0,
      "ponderacion_ranking": 0.0,
      "ponderacion_lenguaje": 0.0,
      "ponderacion_matematicas": 0.0,
      "ponderacion_matematicas_2": 0.0,
      "ponderacion_historia": 0.0,
      "ponderacion_ciencias": 0.0,
      "ponderacion_otros": 0.0
    },
    {
      "codigo_unico_carrera": "I137S1C41J1V1",
      "institucion": {
        "codigo": 137,
        "nombre": "Instituto Profesional EATRI",
        "tipo": "Institutos Profesionales",
        "acreditacion": "Acreditación Extendida",
        "tiene_ficha": true
      },
      "nombre_carrera_programa": "TRADUCCION INGLES ESPAÑOL MENCION CULTURA Y LENGUA PORTUGUESA",
      "nivel_carrera": "Profesional",
      "region": "Metropolitana",
      "jornada": "Diurna",
      "sede": "CASA CENTRAL",
      "arancel_anual_2026": "$ 2.610.000",
      "vacantes_1er_semestre": 25.0,
      "tiene_ponderacion_paes": false,
      "ponderacion_nem": 0.0,
      "ponderacion_ranking": 0.0,
      "ponderacion_lenguaje": 0.0,
      "ponderacion_matematicas": 0.0,
      "ponderacion_matematicas_2": 0.0,
      "ponderacion_historia": 0.0,
      "ponderacion_ciencias": 0.0,
      "ponderacion_otros": 0.0
    },
    {
      "codigo_unico_carrera": "I137S1C42J1V1",
      "institucion": {
        "codigo": 137,
        "nombre": "Instituto Profesional EATRI",
        "tipo": "Institutos Profesionales",
        "acreditacion": "Acreditación Extendida",
        "tiene_ficha": true
      },
      "nombre_carrera_programa": "TRADUCCION INGLES ESPAÑOL MENCION CULTURA Y LENGUA ALEMANA",
      "nivel_carrera": "Profesional",
      "region": "Metropolitana",
      "jornada": "Diurna",
      "sede": "CASA CENTRAL",
      "arancel_anual_2026": "$ 2.610.000",
      "vacantes_1er_semestre": 25.0,
      "tiene_ponderacion_paes": false,
      "ponderacion_nem": 0.0,
      "ponderacion_ranking": 0.0,
      "ponderacion_lenguaje": 0.0,
      "ponderacion_matematicas": 0.0,
      "ponderacion_matematicas_2": 0.0,
      "ponderacion_historia": 0.0,
      "ponderacion_ciencias": 0.0,
      "ponderacion_otros": 0.0
    },
    {
      "codigo_unico_carrera": "I137S1C43J1V1",
      "institucion": {
        "codigo": 137,
        "nombre": "Instituto Profesional EATRI",
        "tipo": "Institutos Profesionales",
        "acreditacion": "Acreditación Extendida",
        "tiene_ficha": true
      },
      "nombre_carrera_programa": "TRADUCCION INGLES ESPAÑOL MENCION CULTURA Y LENGUA FRANCESA",
      "nivel_carrera": "Profesional",
      "region": "Metropolitana",
      "jornada": "Diurna",
      "sede": "CASA CENTRAL",
      "arancel_anual_2026": "$ 2.610.000",
      "vacantes_1er_semestre": 25.0,
      "tiene_ponderacion_paes": false,
      "ponderacion_nem": 0.0,
      "ponderacion_ranking": 0.0,
      "ponderacion_lenguaje": 0.0,
      "ponderacion_matematicas": 0.0,
      "ponderacion_matematicas_2": 0.0,
      "ponderacion_historia": 0.0,
      "ponderacion_ciencias": 0.0,
      "ponderacion_otros": 0.0
    },
    {
      "codigo_unico_carrera": "I137S1C44J1V1",
      "institucion": {
        "codigo": 137,
        "nombre": "Instituto Profesional EATRI",
        "tipo": "Institutos Profesionales",
        "acreditacion": "Acreditación Extendida",
        "tiene_ficha": true
      },
      "nombre_carrera_programa": "INTERPRETACION SIMULTANEA Y CONSECUTIVA INGLES ESPAÑOL",
      "nivel_carrera": "Profesional",
      "region": "Metropolitana",
      "jornada": "Diurna",
      "sede": "CASA CENTRAL",
      "arancel_anual_2026": "$ 2.910.000",
      "vacantes_1er_semestre": 25.0,
      "tiene_ponderacion_paes": false,
      "ponderacion_nem": 0.0,
      "ponderacion_ranking": 0.0,
      "ponderacion_lenguaje": 0.0,
      "ponderacion_matematicas": 0.0,
      "ponderacion_matematicas_2": 0.0,
      "ponderacion_historia": 0.0,
      "ponderacion_ciencias": 0.0,
      "ponderacion_otros": 0.0
    }
  ],
  "indicadores": [
    {
      "institucion": {
        "codigo": 137,
        "nombre": "Instituto Profesional EATRI",
        "tipo": "Institutos Profesionales",
        "acreditacion": "Acreditación Extendida",
        "tiene_ficha": true
      },
      "nombre_carrera_titulo": "Traducción e Interpretariado Simultáneo y Traductor e Intérprete de Enlace",
      "empleabilidad_1er_anio": 0.5,
      "empleabilidad_2do_anio": 0.5287356321839081,
      "retencion_1er_anio": 0.625,
      "continuidad_estudios_pct": 0.07051282051282051,
      "duracion_real_semestres": 11.593749999999991,
      "ingreso_banda_texto": null
    },
    {
      "institucion": {
        "codigo": 89,
        "nombre": "Pontificia Universidad Católica de Valparaíso",
        "tipo": "Universidades",
        "acreditacion": "Acreditada",
        "tiene_ficha": true
      },
      "nombre_carrera_titulo": "Interpretación o Traduccción Inglés - Español",
      "empleabilidad_1er_anio": 0.5138888888888888,
      "empleabilidad_2do_anio": 0.5333333333333333,
      "retencion_1er_anio": 0.7468354430379747,
      "continuidad_estudios_pct": 0.05,
      "duracion_real_semestres": 11.4285714285714,
      "ingreso_banda_texto": null
    },
    {
      "institucion": {
        "codigo": 26,
        "nombre": "Universidad de Artes, Ciencias y Comunicación UNIACC",
        "tipo": "Universidades",
        "acreditacion": "Acreditada",
        "tiene_ficha": true
      },
      "nombre_carrera_titulo": "Traducción e Interpretariado Bilingüe Inglés-Español",
      "empleabilidad_1er_anio": 0.38095238095238093,
      "empleabilidad_2do_anio": 0.42105263157894735,
      "retencion_1er_anio": 0.7523809523809524,
      "continuidad_estudios_pct": 0.06363636363636363,
      "duracion_real_semestres": 12.272727272727302,
      "ingreso_banda_texto": null
    },
    {
      "institucion": {
        "codigo": 87,
        "nombre": "Universidad de Concepción",
        "tipo": "Universidades",
        "acreditacion": "Acreditada",
        "tiene_ficha": true
      },
      "nombre_carrera_titulo": "Traducción/Interpretación en Idiomas Extranjeros",
      "empleabilidad_1er_anio": 0.36082474226804123,
      "empleabilidad_2do_anio": 0.5102040816326531,
      "retencion_1er_anio": 0.9113924050632911,
      "continuidad_estudios_pct": 0.04285714285714286,
      "duracion_real_semestres": null,
      "ingreso_banda_texto": "De $900 mil a $1 millón"
    },
    {
      "institucion": {
        "codigo": 74,
        "nombre": "Universidad de La Serena",
        "tipo": "Universidades",
        "acreditacion": "Acreditada",
        "tiene_ficha": true
      },
      "nombre_carrera_titulo": "Traducción Inglés Español y Licenciatura en Traducción",
      "empleabilidad_1er_anio": 0.3125,
      "empleabilidad_2do_anio": 0.30303030303030304,
      "retencion_1er_anio": 0.90625,
      "continuidad_estudios_pct": 0.1,
      "duracion_real_semestres": null,
      "ingreso_banda_texto": null
    },
    {
      "institucion": {
        "codigo": 19,
        "nombre": "Universidad de Las Américas",
        "tipo": "Universidades",
        "acreditacion": "Acreditada",
        "tiene_ficha": true
      },
      "nombre_carrera_titulo": "Traducción e Intérprete en Inglés",
      "empleabilidad_1er_anio": 0.28488372093023256,
      "empleabilidad_2do_anio": 0.3723404255319149,
      "retencion_1er_anio": 0.8597014925373134,
      "continuidad_estudios_pct": 0.07630522088353414,
      "duracion_real_semestres": 10.360465116279054,
      "ingreso_banda_texto": null
    },
    {
      "institucion": {
        "codigo": 83,
        "nombre": "Universidad de Playa Ancha de Ciencias de la Educación",
        "tipo": "Universidades",
        "acreditacion": "Acreditada",
        "tiene_ficha": true
      },
      "nombre_carrera_titulo": "Traducción e Interpretación Inglés y Español",
      "empleabilidad_1er_anio": 0.4827586206896552,
      "empleabilidad_2do_anio": null,
      "retencion_1er_anio": 0.75,
      "continuidad_estudios_pct": 0.03488372093023256,
      "duracion_real_semestres": null,
      "ingreso_banda_texto": null
    },
    {
      "institucion": {
        "codigo": 54,
        "nombre": "Universidad Tecnológica de Chile INACAP",
        "tipo": "Universidades",
        "acreditacion": "No Acreditada",
        "tiene_ficha": true
      },
      "nombre_carrera_titulo": "Traducción Inglés-Español",
      "empleabilidad_1er_anio": 0.43991416309012876,
      "empleabilidad_2do_anio": 0.5160599571734475,
      "retencion_1er_anio": null,
      "continuidad_estudios_pct": 0.07467532467532467,
      "duracion_real_semestres": 14.979166666666657,
      "ingreso_banda_texto": "De $900 mil a $1 millón"
    }
  ]
}